[
  {
    "type": "decrease",
    "name": "CA BAND",
    "sku": "CA-BAND-XL",
    "qty": 1,
    "status": "success",
    "time": "2026-06-16T12:33:17.611Z"
  },
  {
    "type": "decrease",
    "name": "CA BAND",
    "sku": "CA-BAND-XL",
    "qty": 2,
    "status": "success",
    "time": "2026-06-16T12:33:15.489Z"
  },
  {
    "type": "decrease",
    "name": "CA BAND",
    "sku": "CA-BAND-XL",
    "qty": 3,
    "status": "success",
    "time": "2026-06-16T12:33:11.771Z"
  },
  {
    "type": "decrease",
    "name": "CA BAND",
    "sku": "CA-BAND-XL",
    "qty": 4,
    "status": "success",
    "time": "2026-06-16T12:33:09.172Z"
  },
  {
    "type": "decrease",
    "name": "CA BAND",
    "sku": "CA-BAND-XL",
    "qty": 5,
    "status": "success",
    "time": "2026-06-16T12:33:07.059Z"
  },
  {
    "type": "decrease",
    "name": "CA BAND",
    "sku": "CA-BAND-XL",
    "qty": 6,
    "status": "success",
    "time": "2026-06-16T12:33:04.118Z"
  },
  {
    "type": "arrival",
    "name": "CA BAND",
    "sku": "CA-BAND-XL",
    "qty": 7,
    "status": "success",
    "time": "2026-06-16T12:32:45.969Z"
  },
  {
    "type": "arrival",
    "name": "CA BAND",
    "sku": "CA-BAND-XL",
    "qty": 6,
    "status": "success",
    "time": "2026-06-16T12:32:44.507Z"
  },
  {
    "type": "arrival",
    "name": "CA BAND",
    "sku": "CA-BAND-XL",
    "qty": 5,
    "status": "success",
    "time": "2026-06-16T12:32:43.028Z"
  },
  {
    "type": "arrival",
    "name": "CA BAND",
    "sku": "CA-BAND-XL",
    "qty": 4,
    "status": "success",
    "time": "2026-06-16T12:32:41.842Z"
  },
  {
    "type": "arrival",
    "name": "CA BAND",
    "sku": "CA-BAND-XL",
    "qty": 3,
    "status": "success",
    "time": "2026-06-16T12:32:40.645Z"
  },
  {
    "type": "decrease",
    "name": "CA BAND",
    "sku": "CA-BAND-XL",
    "qty": 2,
    "status": "success",
    "time": "2026-06-16T12:32:29.134Z"
  },
  {
    "type": "arrival",
    "name": "CA BAND",
    "sku": "CA-BAND-XL",
    "qty": 3,
    "status": "success",
    "time": "2026-06-16T12:32:10.569Z"
  },
  {
    "type": "decrease",
    "name": "CA BAND",
    "sku": "CA-BAND-XL",
    "qty": 2,
    "status": "success",
    "time": "2026-06-16T12:31:58.691Z"
  },
  {
    "type": "arrival",
    "name": "CA BAND",
    "sku": "CA-BAND-XL",
    "qty": 3,
    "status": "success",
    "time": "2026-06-16T12:31:42.914Z"
  },
  {
    "type": "decrease",
    "name": "CA BAND",
    "sku": "CA-BAND-XL",
    "qty": 2,
    "status": "success",
    "time": "2026-06-16T12:15:55.306Z"
  },
  {
    "type": "arrival",
    "name": "CA BAND",
    "sku": "CA-BAND-XL",
    "qty": 3,
    "status": "success",
    "time": "2026-06-16T12:15:34.199Z"
  },
  {
    "type": "arrival",
    "name": "TRAJI",
    "sku": "TRAJI-XL",
    "qty": 2,
    "status": "success",
    "time": "2026-06-15T16:43:42.491Z"
  },
  {
    "type": "arrival",
    "name": "CA BAND",
    "sku": "CA-BAND-XL",
    "qty": 2,
    "status": "success",
    "time": "2026-06-15T16:40:07.193Z"
  },
  {
    "type": "decrease",
    "name": "test",
    "sku": "TES-00002",
    "qty": 114,
    "status": "success",
    "time": "2026-06-15T16:10:30.021Z"
  },
  {
    "type": "arrival",
    "name": "test",
    "sku": "TES-00002",
    "qty": 115,
    "status": "success",
    "time": "2026-06-15T16:10:22.164Z"
  },
  {
    "type": "arrival",
    "name": "test",
    "sku": "TES-00002",
    "qty": 114,
    "status": "success",
    "time": "2026-06-15T16:10:21.484Z"
  },
  {
    "type": "decrease",
    "name": "test",
    "sku": "TES-00002",
    "qty": 113,
    "status": "success",
    "time": "2026-06-15T16:05:28.191Z"
  },
  {
    "type": "decrease",
    "name": "test",
    "sku": "TES-00002",
    "qty": 114,
    "status": "success",
    "time": "2026-06-15T16:05:17.364Z"
  },
  {
    "type": "decrease",
    "name": "test",
    "sku": "TES-00002",
    "qty": 115,
    "status": "success",
    "time": "2026-06-15T16:04:58.363Z"
  },
  {
    "type": "arrival",
    "name": "test",
    "sku": "TES-00002",
    "qty": 116,
    "status": "success",
    "time": "2026-06-15T16:04:53.156Z"
  },
  {
    "type": "arrival",
    "name": "test",
    "sku": "TES-00002",
    "qty": 115,
    "status": "success",
    "time": "2026-06-15T16:04:52.594Z"
  },
  {
    "type": "arrival",
    "name": "test",
    "sku": "TES-00002",
    "qty": 1,
    "status": "added",
    "time": "2026-06-15T15:50:46.015Z"
  }
]